MANIFEST.in
README.md
requirements.txt
setup.py
keras_layer_normalization/__init__.py
keras_layer_normalization/layer_normalization.py
keras_layer_normalization.egg-info/PKG-INFO
keras_layer_normalization.egg-info/SOURCES.txt
keras_layer_normalization.egg-info/dependency_links.txt
keras_layer_normalization.egg-info/requires.txt
keras_layer_normalization.egg-info/top_level.txt
tests/__init__.py
tests/test_layer_normalization.py